{
  "seed": 999,
  "tickConfig": {
    "tickUnit": "minute",
    "tickAmount": 1
  },
  "strategyName": "Balanced",
  "predictionModelConfig": {
    "name": "MovingAverage",
    "minBatteryChargeThreshold": 10,
    "productionSafetyFactor": 80,
    "windowSize": 30
  },
  "batteryConfig": {
    "capacity": 1000.0,
    "startingCharge": 0,
    "isPercentage": true
  },
  "energySourcesConfigs": [
    {
      "agentName": "Solar_Array",
      "period": 1440,
      "maxOutputPower": 3000.0,
      "peakTick": 720,
      "stdDev": 100.0,
      "variation": 10
    },
    {
      "agentName": "Wind_Turbine",
      "period": 1440,
      "maxOutputPower": 8000.0,
      "peakTick": 1000,
      "stdDev": 220.0,
      "variation": 40
    },
    {
      "agentName": "Hydro_Plant",
      "period": 1440,
      "maxOutputPower": 12000.0,
      "peakTick": 0,
      "stdDev": 20000.0,
      "variation": 5
    }
  ],
  "householdConfigs": [
    {
      "householdName": "HH_01_Chaos_Family",
      "applianceConfigs": [
        {
          "applianceName": "Kitchen_Gadgets",
          "householdName": "HH_01_Chaos_Family",
          "tasks": [
            {
              "taskName": "BoilKettle",
              "humanActivationChance": 0.25,
              "period": 60,
              "postponable": true,
              "duration": 15,
              "energyPerTick": 2400.0,
              "taskId": 101
            },
            {
              "taskName": "MicrowaveSnack",
              "humanActivationChance": 0.15,
              "period": 120,
              "postponable": false,
              "duration": 15,
              "energyPerTick": 1400.0,
              "taskId": 102
            },
            {
              "taskName": "CoffeeBreak",
              "humanActivationChance": 0.2,
              "period": 180,
              "postponable": true,
              "duration": 15,
              "energyPerTick": 1000.0,
              "taskId": 103
            }
          ]
        },
        {
          "applianceName": "Cleaning_Appliances",
          "householdName": "HH_01_Chaos_Family",
          "tasks": [
            {
              "taskName": "VacuumHouse",
              "humanActivationChance": 0.05,
              "period": 360,
              "postponable": true,
              "duration": 30,
              "energyPerTick": 1600.0,
              "taskId": 104
            },
            {
              "taskName": "Ironing",
              "humanActivationChance": 0.05,
              "period": 720,
              "postponable": true,
              "duration": 45,
              "energyPerTick": 2000.0,
              "taskId": 105
            }
          ]
        },
        {
          "applianceName": "PowerShower",
          "householdName": "HH_01_Chaos_Family",
          "tasks": [
            {
              "taskName": "HotShower",
              "humanActivationChance": 0.8,
              "period": 1440,
              "postponable": false,
              "duration": 15,
              "energyPerTick": 9500.0,
              "taskId": 106
            }
          ]
        },
        {
          "applianceName": "HeatPump",
          "householdName": "HH_01_Chaos_Family",
          "tasks": [
            {
              "taskName": "HeavyHeating",
              "humanActivationChance": 0.9,
              "period": 180,
              "postponable": false,
              "duration": 60,
              "energyPerTick": 4500.0,
              "taskId": 107
            }
          ]
        }
      ]
    },
    {
      "householdName": "HH_02_Tech_Users",
      "applianceConfigs": [
        {
          "applianceName": "Entertainment_Center",
          "householdName": "HH_02_Tech_Users",
          "tasks": [
            {
              "taskName": "QuickGaming",
              "humanActivationChance": 0.3,
              "period": 180,
              "postponable": true,
              "duration": 45,
              "energyPerTick": 600.0,
              "taskId": 201
            },
            {
              "taskName": "SoundSystem",
              "humanActivationChance": 0.4,
              "period": 120,
              "postponable": false,
              "duration": 60,
              "energyPerTick": 300.0,
              "taskId": 202
            }
          ]
        },
        {
          "applianceName": "Bathroom_Gadgets",
          "householdName": "HH_02_Tech_Users",
          "tasks": [
            {
              "taskName": "HairDryer",
              "humanActivationChance": 0.1,
              "period": 720,
              "postponable": false,
              "duration": 15,
              "energyPerTick": 1800.0,
              "taskId": 203
            }
          ]
        },
        {
          "applianceName": "Fast_EV_Charger",
          "householdName": "HH_02_Tech_Users",
          "tasks": [
            {
              "taskName": "Charge_11kW",
              "humanActivationChance": 0.95,
              "period": 1440,
              "postponable": true,
              "duration": 240,
              "energyPerTick": 11000.0,
              "taskId": 204
            }
          ]
        }
      ]
    },
    {
      "householdName": "HH_03_Active_Retired",
      "applianceConfigs": [
        {
          "applianceName": "Kitchen_Small",
          "householdName": "HH_03_Active_Retired",
          "tasks": [
            {
              "taskName": "ToasterBreakfast",
              "humanActivationChance": 0.8,
              "period": 720,
              "postponable": false,
              "duration": 15,
              "energyPerTick": 1200.0,
              "taskId": 301
            },
            {
              "taskName": "TeaTime",
              "humanActivationChance": 0.4,
              "period": 240,
              "postponable": false,
              "duration": 15,
              "energyPerTick": 2400.0,
              "taskId": 302
            }
          ]
        },
        {
          "applianceName": "Laundry",
          "householdName": "HH_03_Active_Retired",
          "tasks": [
            {
              "taskName": "QuickWash",
              "humanActivationChance": 0.2,
              "period": 1440,
              "postponable": true,
              "duration": 45,
              "energyPerTick": 2200.0,
              "taskId": 303
            },
            {
              "taskName": "TumbleDry",
              "humanActivationChance": 0.2,
              "period": 1440,
              "postponable": true,
              "duration": 60,
              "energyPerTick": 2800.0,
              "taskId": 304
            }
          ]
        },
        {
          "applianceName": "Old_Heater",
          "householdName": "HH_03_Active_Retired",
          "tasks": [
            {
              "taskName": "WarmHouse",
              "humanActivationChance": 0.85,
              "period": 360,
              "postponable": true,
              "duration": 90,
              "energyPerTick": 2500.0,
              "taskId": 305
            }
          ]
        }
      ]
    },
    {
      "householdName": "HH_04_Busy_Professional",
      "applianceConfigs": [
        {
          "applianceName": "Home_Office",
          "householdName": "HH_04_Busy_Professional",
          "tasks": [
            {
              "taskName": "Printer",
              "humanActivationChance": 0.1,
              "period": 60,
              "postponable": false,
              "duration": 15,
              "energyPerTick": 600.0,
              "taskId": 401
            },
            {
              "taskName": "WorkLaptop",
              "humanActivationChance": 0.9,
              "period": 1440,
              "postponable": true,
              "duration": 120,
              "energyPerTick": 100.0,
              "taskId": 402
            }
          ]
        },
        {
          "applianceName": "Kitchen_Express",
          "householdName": "HH_04_Busy_Professional",
          "tasks": [
            {
              "taskName": "BlenderSmoothie",
              "humanActivationChance": 0.5,
              "period": 1440,
              "postponable": false,
              "duration": 15,
              "energyPerTick": 800.0,
              "taskId": 403
            },
            {
              "taskName": "CoffeeToGo",
              "humanActivationChance": 0.8,
              "period": 720,
              "postponable": false,
              "duration": 15,
              "energyPerTick": 1200.0,
              "taskId": 404
            }
          ]
        }
      ]
    }
  ]
}